{"inkVersion":20,"root":[["^%FirstNameNPC1% is taking me out to learn to ride my new bike!","\n","^This is the first time I have ever tried riding without stabilizers.","\n","ev","str","^Do everything you're told. You trust %FirstNameNPC1%!","/str","/ev",{"*":"0.c-0","flg":20},"ev","str","^Do what you're told, unless it seems too scary. ","/str","/ev",{"*":"0.c-1","flg":20},"ev","str","^Do it your own way!","/str","/ev",{"*":"0.c-2","flg":20},{"c-0":["\n",{"->":"res1"},{"->":"0.g-0"},{"#f":5}],"c-1":["\n",{"->":"res2"},{"->":"0.g-0"},{"#f":5}],"c-2":["\n",{"->":"res3"},{"->":"0.g-0"},{"#f":5}],"g-0":["done",{"#f":5}]}],"done",{"res1":[["^It turns out that %FirstNameNPC1% has a lot of faith in your abilities. You fall over a few times, and graze your knee, but by the end, you can ride your bike!","\n","ev","str","^I learned to ride my bike today! I did everything I was told, fell off a few times, but hey! Now I can do it!","/str","/ev",{"VAR=":"TextForLog","re":true},"ev","str","^%ValueRef:0:+%","/str","/ev",{"VAR=":"Character0HappinessCh","re":true},"ev","str","^%ValueRef:0:-%","/str","/ev",{"VAR=":"Character0HealthCh","re":true},"ev","str","^%ValueRef:0:+%","/str","/ev",{"VAR=":"Character0EnduranceCh","re":true},"ev","str","^%ValueRef:0:+%","/str","/ev",{"VAR=":"NPC0HappinessCh","re":true},"ev","str","^%ValueRef:0:+%","/str","/ev",{"VAR=":"NPC0RelationshipCh","re":true},"ev","str","^Ok","/str","/ev",{"*":".^.c-0","flg":20},{"c-0":["\n","end",{"#f":5}]}],{"#f":1}],"res2":[["^%FirstNameNPC1% did get a little frustrated with me at times when I insisted that they hold the bike steady for a little. I suppose it did take longer. But... I can now ride my new bike!","\n","ev","str","^I learnt to ride my bike today! Sure, it took me a while, and I was nervous, but who isn't when first getting on a two wheeled deathtrap?","/str","/ev",{"VAR=":"TextForLog","re":true},"ev","str","^%ValueRef:0:+%","/str","/ev",{"VAR=":"Character0HappinessCh","re":true},"ev","str","^%ValueRef:0:+%","/str","/ev",{"VAR=":"Character0EnduranceCh","re":true},"ev","str","^%ValueRef:0:+%","/str","/ev",{"VAR=":"NPC0HappinessCh","re":true},"ev","str","^%ValueRef:0:-%","/str","/ev",{"VAR=":"NPC0RelationshipCh","re":true},"ev","str","^Ok","/str","/ev",{"*":".^.c-0","flg":20},{"c-0":["\n","end",{"#f":5}]}],{"#f":1}],"res3":[["^%FirstNameNPC1% was way too bossy, and I would've hurt myself if I'd done what they told me. Instead, I tried teaching myself how to ride my bike. I am closer, but can't quite ride yet.","\n","ev","str","^I guess I irritated %FirstNameNPC1%... but they were making me way too nervous! Instead, I tried to learn to ride my bike by myself. I'm getting better, but I'm not quite there yet. ","/str","/ev",{"VAR=":"TextForLog","re":true},"ev","str","^%ValueRef:0:-%","/str","/ev",{"VAR=":"Character0HappinessCh","re":true},"ev","str","^%ValueRef:0:+%","/str","/ev",{"VAR=":"Character0HealthCh","re":true},"ev","str","^%ValueRef:0:+%","/str","/ev",{"VAR=":"Character0EnduranceCh","re":true},"ev","str","^%ValueRef:0:-%","/str","/ev",{"VAR=":"NPC0HappinessCh","re":true},"ev","str","^%ValueRef:0:-%","/str","/ev",{"VAR=":"NPC0RelationshipCh","re":true},"ev","str","^Ok","/str","/ev",{"*":".^.c-0","flg":20},{"c-0":["\n","end",{"#f":5}]}],{"#f":1}],"global decl":["ev","str","^","/str",{"VAR=":"StoryTittle"},"str","^This is the first time I have ever tried riding without stabilizers.","/str",{"VAR=":"StoryQuestion"},"str","^","/str",{"VAR=":"StoryCategory"},"str","^","/str",{"VAR=":"TextForLog"},"str","^Kid:PrimarySchool","/str",{"VAR=":"Character0OccupationSc"},3,{"VAR=":"Character0MinAgeSc"},5,{"VAR=":"Character0MaxAgeSc"},"str","^Parent","/str",{"VAR=":"NPC0RelativesSc"},0,{"VAR=":"Character0HappinessCh"},0,{"VAR=":"Character0HealthCh"},0,{"VAR=":"Character0EnduranceCh"},0,{"VAR=":"NPC0HappinessCh"},0,{"VAR=":"NPC0RelationshipCh"},"/ev","end",null],"#f":1}],"listDefs":{}}