{"inkVersion":20,"root":[["^I'm going on a date with %FullName:NPC:1%.","\n","^Which jacket should I wear?","\n","ev","str","^My red jacket","/str","/ev",{"*":"0.c-0","flg":20},"ev","str","^My brown jacket","/str","/ev",{"*":"0.c-1","flg":20},{"c-0":["\n",{"->":"res1"},{"->":"0.g-0"},{"#f":5}],"c-1":["\n",{"->":"res2"},{"->":"0.g-0"},{"#f":5}],"g-0":["done",{"#f":5}]}],"done",{"res1":[["^My red jacket had $40 in it from the last time I wore it, so we use that to make our meal extravagant.","\n","ev","str","^That was like finding a free $40 which was great. I was going to be skimping on dinner but with the extra money I was able to get us everything we wanted plus a big lavish dessert after the meal. And %FullName:NPC:1% loved it!","/str","/ev",{"VAR=":"TextForLog","re":true},"ev","str","^%ValueRef:1:+%","/str","/ev",{"VAR=":"Character0HappinessCh","re":true},"ev","str","^%ValueRef:0:-%","/str","/ev",{"VAR=":"Character0HealthCh","re":true},"ev","str","^%ValueRef:1:+%","/str","/ev",{"VAR=":"NPC0HappinessCh","re":true},"ev","str","^%ValueRef:0:+%","/str","/ev",{"VAR=":"NPC0RelationshipCh","re":true},"ev","str","^Ok","/str","/ev",{"*":".^.c-0","flg":20},{"c-0":["\n","end",{"#f":5}]}],{"#f":1}],"res2":[["^My brown jacket has a hole in it and I look like a mess now.","\n","ev","str","^%FullName:NPC:1% clearly did not like that I showed up with a hole in my jacket. I do look like a mess. Because of this %Pron:1:1% wants to cute the date short and go home. So, I could tell right then and there that the date wasn't going well. And it was even more apparent when %Pron:1:1% told all %Pron:1:2% friends too.","/str","/ev",{"VAR=":"TextForLog","re":true},"ev","str","^%ValueRef:0:-%","/str","/ev",{"VAR=":"Character0HappinessCh","re":true},"ev","str","^%ValueRef:0:-%","/str","/ev",{"VAR=":"Character0PopularityCh","re":true},"ev","str","^%ValueRef:0:-%","/str","/ev",{"VAR=":"NPC0HappinessCh","re":true},"ev","str","^%ValueRef:0:-%","/str","/ev",{"VAR=":"NPC0RelationshipCh","re":true},"ev","str","^Ok","/str","/ev",{"*":".^.c-0","flg":20},{"c-0":["\n","end",{"#f":5}]}],{"#f":1}],"global decl":["ev","str","^","/str",{"VAR=":"StoryTittle"},"str","^Which jacket should I wear?","/str",{"VAR=":"StoryQuestion"},"str","^Cyan","/str",{"VAR=":"StoryCategory"},"str","^","/str",{"VAR=":"TextForLog"},"str","^MiddleSchool:HighSchool","/str",{"VAR=":"Character0OccupationSc"},13,{"VAR=":"Character0MinAgeSc"},18,{"VAR=":"Character0MaxAgeSc"},"str","^Crush","/str",{"VAR=":"NPC0RelationshipSc"},"str","^Opposite","/str",{"VAR=":"NPC0GenderSc"},13,{"VAR=":"NPC0MinAgeSc"},18,{"VAR=":"NPC0MaxAgeSc"},0,{"VAR=":"Character0HappinessCh"},0,{"VAR=":"Character0HealthCh"},0,{"VAR=":"NPC0HappinessCh"},0,{"VAR=":"NPC0RelationshipCh"},0,{"VAR=":"Character0PopularityCh"},"/ev","end",null],"#f":1}],"listDefs":{}}