{"inkVersion":20,"root":[["^Я вчера перебрал спиртного, а сегодня на сцене в театре плохо помню свою роль. Что делать?","\n","ev","str","^Говорить своими словами, импровизировать","/str","/ev",{"*":"0.c-0","flg":20},"ev","str","^Симулировать сердечный приступ и упасть прямо на сцене","/str","/ev",{"*":"0.c-1","flg":20},"ev","str","^Говорить медленно, надеясь на суфлера","/str","/ev",{"*":"0.c-2","flg":20},"ev","str","^Как-бы случайно обрушить декорацию, чтобы сорвать спектакль","/str","/ev",{"*":"0.c-3","flg":20},{"c-0":["\n",{"->":"res1"},{"->":"0.g-0"},{"#f":5}],"c-1":["\n",{"->":"res2"},{"->":"0.g-0"},{"#f":5}],"c-2":["\n",{"->":"res3"},{"->":"0.g-0"},{"#f":5}],"c-3":["\n",{"->":"res4"},{"->":"0.g-0"},{"#f":5}],"g-0":["done",{"#f":5}]}],"done",{"res1":[["^На сцену прилетела кожура от банана, я на ней подскользнулся и упал. Потом меня уволили","\n","ev","str","^Я перебрал спиртного, а наутро, на сцене во время спектакля, плохо помнил свою роль. Я пробовал импровизировать, но это не спасло меня от фиаско.","/str","/ev",{"VAR=":"TextForLog","re":true},"ev","str","^Ok","/str","/ev",{"*":".^.c-0","flg":20},{"c-0":["\n","end",{"#f":5}]}],{"#f":1}],"res2":[["^Этим мне удалось скрыть свой проступок, более того, из-за сочувствия окружающих, моя популярность возросла","\n","ev","str","^Я перебрал спиртного, а наутро, на сцене во время спектакля, плохо помнил свою роль. Я симулировал сердечный приступ на сцене, это спасло меня от фиаско и даже добавило популярности.","/str","/ev",{"VAR=":"TextForLog","re":true},"ev","str","^Ok","/str","/ev",{"*":".^.c-0","flg":20},{"c-0":["\n","end",{"#f":5}]}],{"#f":1}],"res3":[["^Мне удалось дотянуть действие до антракта. А там я сумел подучить слова и нормально закончить спектакль","\n","ev","str","^Я перебрал спиртного, а наутро, на сцене во время спектакля, плохо помнил свою роль. Я выкрутился с помощью суфлера.","/str","/ev",{"VAR=":"TextForLog","re":true},"ev","str","^Ok","/str","/ev",{"*":".^.c-0","flg":20},{"c-0":["\n","end",{"#f":5}]}],{"#f":1}],"res4":[["^У меня были неприятности, но ситуацию списали на случайность. Больше подобного не допущу","\n","ev","str","^Я перебрал спиртного, а наутро, на сцене во время спектакля, плохо помнил свою роль. Я имитировал случайное обрушение декорации. Это спасло меня от позора, но сорвало спектакль.","/str","/ev",{"VAR=":"TextForLog","re":true},"ev","str","^Ok","/str","/ev",{"*":".^.c-0","flg":20},{"c-0":["\n","end",{"#f":5}]}],{"#f":1}],"global decl":["ev",30,{"VAR=":"AgeMinCondition"},50,{"VAR=":"AgeMaxCondition"},"str","^Male","/str",{"VAR=":"SexCondition"},"str","^Работа","/str",{"VAR=":"GroupTitle"},"str","^Actor","/str",{"VAR=":"ProfessionalType"},"str","^","/str",{"VAR=":"TextForLog"},0,{"VAR=":"ChangeHappiness"},0,{"VAR=":"ChangeLooks"},0,{"VAR=":"ChangeSmarts"},0,{"VAR=":"ChangeHealth"},"/ev","end",null],"#f":1}],"listDefs":{}}