{"inkVersion":20,"root":[["^Я хотела играть в мамином шкафу, но она сказала, чтоб я этого не делала, так как там сидит злой дядька. Что делать?","\n","ev","str","^Она меня просто пугает. Дождусь, когда мама уйдет и буду играть в шкафу","/str","/ev",{"*":"0.c-0","flg":20},"ev","str","^Попрошу папу выгнать дядьку из шкафа","/str","/ev",{"*":"0.c-1","flg":20},"ev","str","^Не буду играть в шкафу, я боюсь злого дядьку","/str","/ev",{"*":"0.c-2","flg":20},"ev","str","^Возьму мамин баллончик с перцовкой и распылю в шкафу, чтоб выгнать дядьку","/str","/ev",{"*":"0.c-3","flg":20},{"c-0":["\n",{"->":"res1"},{"->":"0.g-0"},{"#f":5}],"c-1":["\n",{"->":"res2"},{"->":"0.g-0"},{"#f":5}],"c-2":["\n",{"->":"res3"},{"->":"0.g-0"},{"#f":5}],"c-3":["\n",{"->":"res4"},{"->":"0.g-0"},{"#f":5}],"g-0":["done",{"#f":5}]}],"done",{"res1":[["^Мама - врушка. Не было там дядьки. Я весело провела время, играя в шкафу","\n","ev","str","^Я хотела играть в мамином шкафу, но она сказала, чтоб я этого не делала, так как там сидит злой дядька. Я ей не поверила и прекрасно поиграла в шкафу.","/str","/ev",{"VAR=":"TextForLog","re":true},"ev","str","^Ok","/str","/ev",{"*":".^.c-0","flg":20},{"c-0":["\n","end",{"#f":5}]}],{"#f":1}],"res2":[["^Папа сильно разозлился на маму. Мама стала его убеждать, что никакого дядьки не было, но он ей не поверил. Ничего не понимаю","\n","ev","str","^Я хотела играть в мамином шкафу, но она сказала, чтоб я этого не делала, так как там сидит злой дядька. Я попросила папу выгнать дядьку из маминого шкафа и папа жутко рассердился на маму.","/str","/ev",{"VAR=":"TextForLog","re":true},"ev","str","^Ok","/str","/ev",{"*":".^.c-0","flg":20},{"c-0":["\n","end",{"#f":5}]}],{"#f":1}],"res3":[["^Я больше не лазаю в мамин шкаф, но мне часто снится злой дядька из шкафа. И тогда я просыпаюсь с криком","\n","ev","str","^Я хотела играть в мамином шкафу, но она сказала, чтоб я этого не делала, так как там сидит злой дядька. Я больше не лазаю в мамин шкаф, но мне часто снится злой дядька из шкафа. И тогда я просыпаюсь с криком.","/str","/ev",{"VAR=":"TextForLog","re":true},"ev","str","^Ok","/str","/ev",{"*":".^.c-0","flg":20},{"c-0":["\n","end",{"#f":5}]}],{"#f":1}],"res4":[["^Я хотела, как лучше, но мама сильно расстроилась. Сказала, что теперь ее вещи плохо пахнут.","\n","ev","str","^Я хотела играть в мамином шкафу, но она сказала, чтоб я этого не делала, так как там сидит злой дядька. Я распылила перцовку в мамином шкафу, чтобы выгнать дядьку. Мама сильно расстроилась, так как ее вещи стали дурно пахнуть.","/str","/ev",{"VAR=":"TextForLog","re":true},"ev","str","^Ok","/str","/ev",{"*":".^.c-0","flg":20},{"c-0":["\n","end",{"#f":5}]}],{"#f":1}],"global decl":["ev",5,{"VAR=":"AgeMinCondition"},7,{"VAR=":"AgeMaxCondition"},"str","^Female","/str",{"VAR=":"SexCondition"},"str","^Улица","/str",{"VAR=":"GroupTitle"},"str","^","/str",{"VAR=":"TextForLog"},0,{"VAR=":"ChangeHappiness"},0,{"VAR=":"ChangeLooks"},0,{"VAR=":"ChangeSmarts"},0,{"VAR=":"ChangeHealth"},"/ev","end",null],"#f":1}],"listDefs":{}}